Metadata-Version: 1.1
Name: pyRMT
Version: 0.1.0
Summary: Python for Random Matrix Theory: cleaning schemes for noisy correlation matrices
Home-page: https://github.com/GGiecold/pyRMT
Author: Gregory Giecold
Author-email: g.giecold@gmail.com
License: MIT License
Download-URL: https://github.com/GGiecold/pyRMT
Keywords: applied-mathematics cleaning correlation-matrices noise-reduction random-matrix-theory
Platform: ALL
Classifier: Development Status :: 4 - Beta
Classifier: Environment :: Console
Classifier: Intended Audience :: End Users/Desktop
Classifier: Intended Audience :: Developers
Classifier: Intended Audience :: Science/Research
Classifier: License :: OSI Approved :: MIT License
Classifier: Natural Language :: English
Classifier: Operating System :: OS Independent
Classifier: Programming Language :: Python
Classifier: Topic :: Scientific/Engineering
Classifier: Topic :: Scientific/Engineering :: Mathematics
